ParProcCo/__init__.py
ParProcCo/aggregator_interface.py
ParProcCo/data_slicer_interface.py
ParProcCo/job_controller.py
ParProcCo/job_scheduler.py
ParProcCo/job_scheduling_information.py
ParProcCo/job_slicer_interface.py
ParProcCo/nxdata_aggregation_slicer.py
ParProcCo/nxdata_aggregator.py
ParProcCo/passthru_wrapper.py
ParProcCo/program_wrapper.py
ParProcCo/simple_data_slicer.py
ParProcCo/utils.py
ParProcCo/slurm/__init__.py
ParProcCo/slurm/generate_models.py
ParProcCo/slurm/slurm_client.py
ParProcCo/slurm/slurm_rest.py
ParProcCo/slurm/slurmdb_rest.py
ParProcCo/test/__init__.py
ParProcCo-2.1.2.data/scripts/nxdata_aggregate
ParProcCo-2.1.2.data/scripts/ppc_cluster_runner
ParProcCo-2.1.2.data/scripts/ppc_cluster_submit
ParProcCo-2.1.2.dist-info/LICENSE
ParProcCo-2.1.2.dist-info/METADATA
ParProcCo-2.1.2.dist-info/WHEEL
ParProcCo-2.1.2.dist-info/top_level.txt
ParProcCo-2.1.2.dist-info/RECORD
