Metadata-Version: 2.1
Name: ParProcCo
Version: 2.1.2
Summary: Parallel Processing Coordinator. Splits dataset processing to run parallel cluster jobs and aggregates outputs
Home-page: https://github.com/DiamondLightSource/ParProcCo
Author-email: dataanalysis@diamond.ac.uk
Requires-Python: >=3.10
License-File: LICENSE
Requires-Dist: h5py
Requires-Dist: pydantic
Requires-Dist: pyyaml
Requires-Dist: requests
Provides-Extra: dev
Requires-Dist: datamodel-code-generator ; extra == 'dev'
Provides-Extra: testing
Requires-Dist: parameterized ; extra == 'testing'
Requires-Dist: pytest ; extra == 'testing'
